CHANGELOG.txt
LICENCE.txt
MANIFEST.in
readme.txt
setup.py
log4me/__init__.py
log4me/test.py
log4me.egg-info/PKG-INFO
log4me.egg-info/SOURCES.txt
log4me.egg-info/dependency_links.txt
log4me.egg-info/requires.txt
log4me.egg-info/top_level.txt