Metadata-Version: 2.1
Name: log4me
Version: 0.0.3
Summary: Basic logger for personal python projects
Home-page: https://github.com/LucasHahmann/log4me
Author: Lucas Hahmann
Author-email: lucas@hahmann-trier.de
License: MIT
Keywords: logger
Platform: UNKNOWN
Classifier: Development Status :: 5 - Production/Stable
Classifier: Intended Audience :: Education
Classifier: Operating System :: Microsoft :: Windows :: Windows 10
Classifier: License :: OSI Approved :: MIT License
Classifier: Programming Language :: Python :: 3
License-File: LICENCE.txt
